hello_labdata_dl/__init__.py
hello_labdata_dl/_modidx.py
hello_labdata_dl/greetings.py
hello_labdata_dl/jokes.py
hello_labdata_dl-0.0.1.dist-info/LICENSE
hello_labdata_dl-0.0.1.dist-info/METADATA
hello_labdata_dl-0.0.1.dist-info/WHEEL
hello_labdata_dl-0.0.1.dist-info/entry_points.txt
hello_labdata_dl-0.0.1.dist-info/top_level.txt
hello_labdata_dl-0.0.1.dist-info/RECORD
